cnlp_cli/__init__.py
cnlp_cli/version.py
cnlp_cli/shell/__init__.py
cnlp_cli/shell/usage.py
cnlp_cli-0.0.1.dist-info/METADATA
cnlp_cli-0.0.1.dist-info/RECORD
cnlp_cli-0.0.1.dist-info/WHEEL
cnlp_cli-0.0.1.dist-info/entry_points.txt
cnlp_cli-0.0.1.dist-info/top_level.txt
cnlp_cli-0.0.1.dist-info/zip-safe
