Metadata-Version: 2.1
Name: cnlp-cli
Version: 0.0.1
Summary: cnlp-cli is CNLP Command Line Interface, which is a submodule of cnlp.
Home-page: https://github.com/dovolopor-research/cnlp-cli
Author: Ailln
Author-email: dovolopor@gmail.com
License: MIT License
Platform: UNKNOWN
Classifier: Programming Language :: Python :: 3
Classifier: License :: OSI Approved :: MIT License
Classifier: Operating System :: OS Independent
Requires-Python: >=3.6
Requires-Dist: setuptools (>=40.6.3)
